TiVaCPD/__init__.py
TiVaCPD/cpd_methods.py
TiVaCPD/distribution_changes.py
TiVaCPD/exp_2.py
TiVaCPD/experiments.py
TiVaCPD/load_data.py
TiVaCPD/main.py
TiVaCPD/performance.py
TiVaCPD/simulate.py
TiVaCPD/tvgl.py
TiVaCPD-1.0.0.dist-info/LICENSE
TiVaCPD-1.0.0.dist-info/METADATA
TiVaCPD-1.0.0.dist-info/WHEEL
TiVaCPD-1.0.0.dist-info/top_level.txt
TiVaCPD-1.0.0.dist-info/RECORD
