Metadata-Version: 2.1
Name: TiVaCPD
Version: 1.0.0
Summary: Time-Varying Change Point Detection
Home-page: https://github.com/kopalgarg/TiVaCPD
Author: Kopal Garg
Author-email: gargkopal24@gmail.com
Classifier: Programming Language :: Python :: 3
Classifier: License :: OSI Approved :: MIT License
Classifier: Operating System :: OS Independent
License-File: LICENSE
